tme/__init__.py
tme/base_jax.py
tme/base_sympy.py
tme/base_tf.py
tme/experimental.py
tme/typings.py
tme-0.2.0.dist-info/LICENSE
tme-0.2.0.dist-info/METADATA
tme-0.2.0.dist-info/WHEEL
tme-0.2.0.dist-info/top_level.txt
tme-0.2.0.dist-info/RECORD
