Metadata-Version: 2.1
Name: tme
Version: 0.2.0
Summary: Taylor moment expansion in Python
Author-email: Zheng Zhao <zz@zabemon.com>
License: Taylor moment expansion (TME) in Python
Project-URL: homepage, https://github.com/zgbkdlm/tme
Project-URL: documentation, https://tme.readthedocs.io
Project-URL: repository, https://github.com/zgbkdlm/tme
Keywords: Markov models,stochastic differential equations,statistics
Classifier: Programming Language :: Python :: 3
Classifier: License :: OSI Approved :: GNU General Public License v3 or later (GPLv3+)
Classifier: Operating System :: OS Independent
Classifier: Intended Audience :: Science/Research
Classifier: Intended Audience :: Developers
Classifier: Topic :: Scientific/Engineering :: Artificial Intelligence
Classifier: Topic :: Scientific/Engineering :: Information Analysis
Classifier: Topic :: Scientific/Engineering :: Mathematics
Requires-Python: >=3.8
License-File: LICENSE
Requires-Dist: numpy>=1.19.2
Requires-Dist: scipy>=1.5.2
Requires-Dist: sympy>=1.8
Provides-Extra: test
Requires-Dist: pytest==8.3.3; extra == "test"
